autoneuro_pypi/__init__.py
autoneuro_pypi/__main__.py
autoneuro_pypi/pneuro.py
autoneuro_pypi/test.py
autoneuro_pypi/dataLoad/__init__.py
autoneuro_pypi/dataLoad/data_loader.py
autoneuro_pypi/dataPreprocessing/__init__.py
autoneuro_pypi/dataPreprocessing/preProcess.py
autoneuro_pypi/dataVisualization/__init__.py
autoneuro_pypi/dataVisualization/visualization.py
autoneuro_pypi/fileOperations/__init__.py
autoneuro_pypi/fileOperations/file_methods.py
autoneuro_pypi/logger/__init__.py
autoneuro_pypi/logger/appLogger.py
autoneuro_pypi/logs/__init__.py
autoneuro_pypi/modelTraining/__init__.py
autoneuro_pypi/modelTraining/classificationModels.py
autoneuro_pypi/modelTraining/regressionModels.py
autoneuro_pypi/prediction/__init__.py
autoneuro_pypi/prediction/predict.py
autoneuro_pypi/static/__init__.py
autoneuro_pypi/templates/__init__.py
autoneuro_pypi-1.0.0.dist-info/LICENSE.txt
autoneuro_pypi-1.0.0.dist-info/METADATA
autoneuro_pypi-1.0.0.dist-info/WHEEL
autoneuro_pypi-1.0.0.dist-info/entry_points.txt
autoneuro_pypi-1.0.0.dist-info/top_level.txt
autoneuro_pypi-1.0.0.dist-info/RECORD
